mdmm/__init__.py
mdmm/mdmm.py
mdmm-0.1.3.dist-info/LICENSE
mdmm-0.1.3.dist-info/METADATA
mdmm-0.1.3.dist-info/WHEEL
mdmm-0.1.3.dist-info/top_level.txt
mdmm-0.1.3.dist-info/RECORD
