Metadata-Version: 2.1
Name: mdmm
Version: 0.1.3
Summary: The Modified Differential Multiplier Method (MDMM) for PyTorch.
Home-page: https://github.com/crowsonkb/mdmm
Author: Katherine Crowson
Author-email: crowsonkb@gmail.com
License: MIT
Platform: UNKNOWN
Classifier: Development Status :: 3 - Alpha
Classifier: Intended Audience :: Developers
Classifier: Intended Audience :: Science/Research
Classifier: License :: OSI Approved :: MIT License
Classifier: Programming Language :: Python :: 3.6
Classifier: Programming Language :: Python :: 3.7
Classifier: Programming Language :: Python :: 3.8
Classifier: Programming Language :: Python :: 3.9
Classifier: Programming Language :: Python :: 3.10
Classifier: Topic :: Scientific/Engineering :: Artificial Intelligence
Classifier: Topic :: Scientific/Engineering :: Mathematics
Requires-Python: >=3.6
Requires-Dist: torch (>=1.7.1)
Requires-Dist: dataclasses (>=0.8) ; python_version < "3.7"
